{
  "global": {
    "primary700": {
      "value": "#4D1945",
      "type": "color"
    },
    "primary600": {
      "value": "#783C6E",
      "type": "color"
    },
    "primary500": {
      "value": "#9A6190",
      "type": "color"
    },
    "sm": {
      "value": "4",
      "type": "borderRadius"
    },
    "md": {
      "value": "{sm} * 2",
      "type": "borderRadius"
    },
    "lg": {
      "value": "{sm} * 3",
      "type": "borderRadius"
    },
    "h1": {
      "value": "40",
      "type": "fontSizes"
    },
    "h2": {
      "value": "30",
      "type": "fontSizes"
    },
    "h3": {
      "value": "20",
      "type": "fontSizes"
    }
  },
  "dropdown": {
    "dropdown-border-radius": {
      "value": "10",
      "type": "borderRadius"
    },
    "black": {
      "value": "#000000",
      "type": "color"
    }
  }
}